mongodb_connect/__init__.py
mongodb_connect/connect.py
mongodb_connect/mongo_crud.py
mongopy_conn-0.0.1.dist-info/LICENSE
mongopy_conn-0.0.1.dist-info/METADATA
mongopy_conn-0.0.1.dist-info/WHEEL
mongopy_conn-0.0.1.dist-info/top_level.txt
mongopy_conn-0.0.1.dist-info/RECORD
